[{"_path":"/modules/publication/discussion","_dir":"publication","_draft":false,"_partial":false,"_locale":"","title":"Discussion","description":"","_type":"markdown","_id":"github:modules:publication:discussion.md","_source":"github","_file":"modules/publication/discussion.md","_extension":"md"},{"_path":"/modules/publication/software_publication_pipeline","_dir":"publication","_draft":false,"_partial":false,"_locale":"","title":"Software publication pipeline","description":"","_type":"markdown","_id":"github:modules:publication:software_publication_pipeline.md","_source":"github","_file":"modules/publication/software_publication_pipeline.md","_extension":"md"}]