[{"_path":"/modules/researchsoftware/slides-researchsoftware","_dir":"researchsoftware","_draft":false,"_partial":false,"_locale":"","title":"Research software","description":"","_type":"markdown","_id":"github:modules:researchsoftware:slides-researchsoftware.md","_source":"github","_file":"modules/researchsoftware/slides-researchsoftware.md","_extension":"md"},{"_path":"/modules/researchsoftware/software-and-data","_dir":"researchsoftware","_draft":false,"_partial":false,"_locale":"","title":"Software And Data","description":"","_type":"markdown","_id":"github:modules:researchsoftware:software-and-data.md","_source":"github","_file":"modules/researchsoftware/software-and-data.md","_extension":"md"}]