[{"_path":"/modules/citation/citationcff","_dir":"citation","_draft":false,"_partial":false,"_locale":"","title":"CITATION.cff file","description":"","type":"reading","order":4,"_type":"markdown","_id":"local_fs:modules:citation:citationcff.md","_source":"local_fs","_file":"modules/citation/citationcff.md","_extension":"md"},{"_path":"/modules/citation/ex_when_to_cite","_dir":"citation","_draft":false,"_partial":false,"_locale":"","title":"What to cite?","description":"","type":"exercise","order":6,"_type":"markdown","_id":"local_fs:modules:citation:ex_when_to_cite.md","_source":"local_fs","_file":"modules/citation/ex_when_to_cite.md","_extension":"md"}]