[{"_path":"/modules/publication/media/slides-publication","_dir":"media","_draft":false,"_partial":false,"_locale":"","title":"Publishing Software","description":"","_type":"markdown","_id":"github:modules:publication:media:slides-publication.md","_source":"github","_file":"modules/publication/media/slides-publication.md","_extension":"md"},{"_path":"/modules/researchsoftware/media/slides-researchsoftware","_dir":"media","_draft":false,"_partial":false,"_locale":"","title":"Research software","description":"","_type":"markdown","_id":"github:modules:researchsoftware:media:slides-researchsoftware.md","_source":"github","_file":"modules/researchsoftware/media/slides-researchsoftware.md","_extension":"md"}]